fastapi_gen8/__about__.py
fastapi_gen8/__init__.py
fastapi_gen8/helpers.py
fastapi_gen8/main.py
fastapi_gen8-0.0.9.dist-info/METADATA
fastapi_gen8-0.0.9.dist-info/WHEEL
fastapi_gen8-0.0.9.dist-info/entry_points.txt
fastapi_gen8-0.0.9.dist-info/licenses/LICENSE
fastapi_gen8-0.0.9.dist-info/RECORD
