Metadata-Version: 2.4
Name: fastapi-gen8
Version: 0.0.9
Summary: FastAPI Project Gen8 is a lightweight command-line tool designed to generate clean, structured, production-ready FastAPI project scaffolds at warp speed
Project-URL: Documentation, https://github.com/Brian Obot/fastapi-gen8#README.md
Project-URL: Issues, https://github.com/Brian Obot/fastapi-gen8/issues
Project-URL: Source, https://github.com/Brian Obot/fastapi-gen8
Author-email: Brian Obot <brianobot@gmail.com>
License-Expression: MIT
License-File: LICENSE
Classifier: Development Status :: 4 - Beta
Classifier: Programming Language :: Python
Classifier: Programming Language :: Python :: 3.8
Classifier: Programming Language :: Python :: 3.9
Classifier: Programming Language :: Python :: 3.10
Classifier: Programming Language :: Python :: 3.11
Classifier: Programming Language :: Python :: 3.12
Classifier: Programming Language :: Python :: Implementation :: CPython
Classifier: Programming Language :: Python :: Implementation :: PyPy
Requires-Python: >=3.8
Requires-Dist: faker
Requires-Dist: pytest
